rapidnlp_datasets/__init__.py
rapidnlp_datasets/charlevel_tokenizer.py
rapidnlp_datasets/dureader.py
rapidnlp_datasets/masked_lm.py
rapidnlp_datasets/question_answering.py
rapidnlp_datasets/readers.py
rapidnlp_datasets/sequence_classification.py
rapidnlp_datasets/simcse.py
rapidnlp_datasets/token_classification.py
rapidnlp_datasets/utils_tf.py
rapidnlp_datasets/pt/__init__.py
rapidnlp_datasets/pt/dataset.py
rapidnlp_datasets/pt/masked_lm_dataset.py
rapidnlp_datasets/pt/question_answering_dataset.py
rapidnlp_datasets/pt/sequence_classification_dataset.py
rapidnlp_datasets/pt/simcse_dataset.py
rapidnlp_datasets/pt/token_classification_dataset.py
rapidnlp_datasets/pt/utils.py
rapidnlp_datasets/tf/__init__.py
rapidnlp_datasets/tf/dataset.py
rapidnlp_datasets/tf/masked_lm_dataset.py
rapidnlp_datasets/tf/question_answering_dataset.py
rapidnlp_datasets/tf/sequence_classification_dataset.py
rapidnlp_datasets/tf/simcse_dataset.py
rapidnlp_datasets/tf/token_classification_dataset.py
rapidnlp_datasets/tf/utils.py
tests/__init__.py
tests/charlevel_tokenizer_test.py
tests/masked_lm_test.py
tests/question_answering_test.py
tests/sequence_classification_test.py
tests/simcse_test.py
tests/token_classification_test.py
rapidnlp_datasets-0.2.0.dist-info/LICENSE
rapidnlp_datasets-0.2.0.dist-info/METADATA
rapidnlp_datasets-0.2.0.dist-info/WHEEL
rapidnlp_datasets-0.2.0.dist-info/top_level.txt
rapidnlp_datasets-0.2.0.dist-info/RECORD
