Metadata-Version: 2.1
Name: rapidnlp-datasets
Version: 0.2.0
Summary: Data pipelines for TensorFlow and PyTorch.
Home-page: https://github.com/naivenlp/rapidnlp-datasets
Author: ZhouYang Luo
Author-email: zhouyang.luo@gmail.com
License: Apache Software License
Platform: UNKNOWN
Classifier: Programming Language :: Python :: 3
Classifier: Programming Language :: Python :: 3.5
Classifier: Programming Language :: Python :: 3.6
Classifier: Programming Language :: Python :: 3.7
Classifier: Programming Language :: Python :: 3.8
Classifier: Programming Language :: Python :: 3.9
Classifier: License :: OSI Approved :: Apache Software License
Classifier: Operating System :: OS Independent
Classifier: Topic :: Scientific/Engineering :: Artificial Intelligence
License-File: LICENSE
Requires-Dist: tokenizers
Provides-Extra: pt
Requires-Dist: torch ; extra == 'pt'
Requires-Dist: torchaudio ; extra == 'pt'
Requires-Dist: torchvision ; extra == 'pt'
Provides-Extra: tf
Requires-Dist: tensorflow ; extra == 'tf'
